{"cik":1365135,"taxonomy":"us-gaap","tag":"LongTermDebt","label":"Long-term Debt","description":"Amount, after unamortized (discount) premium and debt issuance costs, of long-term debt. Includes, but not limited to, notes payable, bonds payable, debentures, mortgage loans and commercial paper. Excludes capital lease obligations.","entityName":"Western Union CO","units":{"USD":[{"end":"2021-03-31","val":3250000000,"accn":"0001558370-21-005716","fy":2021,"fp":"Q1","form":"10-Q","filed":"2021-05-04","frame":"CY2021Q1I"},{"end":"2021-06-30","val":2750000000,"accn":"0001558370-21-010208","fy":2021,"fp":"Q2","form":"10-Q","filed":"2021-08-04","frame":"CY2021Q2I"}]}}