{"cik":47217,"taxonomy":"us-gaap","tag":"LongTermDebt","label":"Long-term Debt","description":"Amount, after unamortized (discount) premium and debt issuance costs, of long-term debt. Includes, but not limited to, notes payable, bonds payable, debentures, mortgage loans and commercial paper. Excludes capital lease obligations.","entityName":"HP Inc.","units":{"USD":[{"end":"2010-10-31","val":16777000000,"accn":"0001047469-10-010444","fy":2010,"fp":"FY","form":"10-K","filed":"2010-12-15","frame":"CY2010Q3I"},{"end":"2011-10-31","val":26339000000,"accn":"0001047469-11-010094","fy":2011,"fp":"FY","form":"10-K","filed":"2011-12-14","frame":"CY2011Q3I"},{"end":"2012-10-31","val":27132000000,"accn":"0001047469-12-011417","fy":2012,"fp":"FY","form":"10-K","filed":"2012-12-27","frame":"CY2012Q3I"},{"end":"2020-10-31","val":6261000000,"accn":"0000047217-20-000045","fy":2020,"fp":"FY","form":"10-K","filed":"2020-12-10","frame":"CY2020Q3I"}]}}