{"cik":1585364,"taxonomy":"us-gaap","tag":"LongTermDebt","label":"Long-term Debt","description":"Amount, after unamortized (discount) premium and debt issuance costs, of long-term debt. Includes, but not limited to, notes payable, bonds payable, debentures, mortgage loans and commercial paper. Excludes capital lease obligations.","entityName":"Perrigo Company plc","units":{"USD":[{"end":"2015-06-27","val":820900000,"accn":"0001585364-15-000156","fy":2016,"fp":"Q1","form":"10-Q","filed":"2015-11-02","frame":"CY2015Q2I"},{"end":"2015-06-27","val":820900000,"accn":"0001585364-15-000100","fy":2015,"fp":"FY","form":"10-K","filed":"2015-08-13"},{"end":"2015-09-26","val":822700000,"accn":"0001585364-15-000156","fy":2016,"fp":"Q1","form":"10-Q","filed":"2015-11-02","frame":"CY2015Q3I"}]}}