{"cik":1413329,"taxonomy":"us-gaap","tag":"CommonStockSharesOutstanding","label":"Common Stock, Shares, Outstanding","description":"Number of shares of common stock outstanding. Common stock represent the ownership interest in a corporation.","entityName":"Philip Morris International Inc.","units":{"shares":[{"end":"2008-03-28","val":2108901789,"accn":"0001193125-11-046772","fy":2010,"fp":"FY","form":"10-K","filed":"2011-02-25","frame":"CY2008Q1I"},{"end":"2008-12-31","val":2007263060,"accn":"0001193125-11-046772","fy":2010,"fp":"FY","form":"10-K","filed":"2011-02-25","frame":"CY2008Q4I"},{"end":"2009-12-31","val":1887164503,"accn":"0001193125-11-046772","fy":2010,"fp":"FY","form":"10-K","filed":"2011-02-25","frame":"CY2009Q4I"},{"end":"2010-12-31","val":1801783490,"accn":"0001193125-11-046772","fy":2010,"fp":"FY","form":"10-K","filed":"2011-02-25","frame":"CY2010Q4I"}]}}